mask_recognition/__init__.py
mask_recognition/mask_recognition.py
mask_recognition/networks.py
mask_recognition/model/model.pth
mask_recognition-0.0.1.dist-info/METADATA
mask_recognition-0.0.1.dist-info/WHEEL
mask_recognition-0.0.1.dist-info/dependency_links.txt
mask_recognition-0.0.1.dist-info/top_level.txt
mask_recognition-0.0.1.dist-info/RECORD
