Metadata-Version: 2.1
Name: mask-recognition
Version: 0.0.1
Summary: It recognize the face mask on human on the image
Home-page: https://github.com/Rayyan-Akhtar/mask_recognition
Author: Rayyan Akhtar
Author-email: akhtar.rayyan@live.com
License: MIT
Keywords: Recognition,Face Mask,Neural Network,Pytorch
Platform: UNKNOWN
Classifier: License :: OSI Approved :: MIT License
Classifier: Programming Language :: Python :: 3
Classifier: Programming Language :: Python :: 3.6
Classifier: Programming Language :: Python :: 3.7
Requires-Python: >=3.6
Requires-Dist: facenet-pytorch
Requires-Dist: opencv-python (>=3.4.2)
Requires-Dist: numpy (>=1.18.1)
